googledrive/__init__.py
googledrive/api.py
googledrive/cli.py
googledrive/exceptions.py
googledrive/mappers.py
googledrive/models.py
google_drive-0.5.1.dist-info/LICENSE
google_drive-0.5.1.dist-info/METADATA
google_drive-0.5.1.dist-info/WHEEL
google_drive-0.5.1.dist-info/entry_points.txt
google_drive-0.5.1.dist-info/top_level.txt
google_drive-0.5.1.dist-info/RECORD
