Metadata-Version: 2.1
Name: google-drive
Version: 0.5.1
Summary: Library and cli to manage and interact with your Google Drive
Home-page: https://github.com/eduardogr/google-drive-python
Author: Eduardo Garcia
Author-email: garciaruiz.edu+maintain+google-drive-python@gmail.com
Maintainer: Eduardo García
Maintainer-email: garciaruiz.edu+google-drive-python@gmail.com
License: Apache
Keywords: google drive
Classifier: Development Status :: 5 - Production/Stable
Classifier: Topic :: Software Development :: Libraries
Classifier: License :: OSI Approved :: Apache Software License
License-File: LICENSE
Requires-Dist: google-api-core ==1.31.5
Requires-Dist: google-api-python-client ==2.6.0
Requires-Dist: google-auth ==1.35.0
Requires-Dist: google-auth-httplib2 ==0.1.0
Requires-Dist: google-auth-oauthlib ==0.4.1
Requires-Dist: googleapis-common-protos ==1.56.0
Requires-Dist: dataclasses ==0.6
Requires-Dist: click ==8.1.7
Provides-Extra: dev
Requires-Dist: pylint ==2.16.0b1 ; extra == 'dev'
Requires-Dist: autopep8 ==2.0.1 ; extra == 'dev'
Requires-Dist: pytest ==7.2.1 ; extra == 'dev'
Requires-Dist: pytest-cov ==4.0.0 ; extra == 'dev'
Requires-Dist: ipython ==7.23.1 ; extra == 'dev'
Requires-Dist: codecov ==2.1.12 ; extra == 'dev'
Requires-Dist: twine ==4.0.2 ; extra == 'dev'
